phoopy/__init__.py
phoopy/phoopy/__init__.py
phoopy-1.3.0.dist-info/LICENSE.md
phoopy-1.3.0.dist-info/METADATA
phoopy-1.3.0.dist-info/WHEEL
phoopy-1.3.0.dist-info/top_level.txt
phoopy-1.3.0.dist-info/RECORD
