Metadata-Version: 2.1
Name: phoopy
Version: 1.3.0
Summary: Full stack framework for python based on bundles
Home-page: https://github.com/phoopy/phoopy
Author: Phoopy
Author-email: reisraff@gmail.com
License: MIT
Platform: UNKNOWN
Classifier: Operating System :: OS Independent
Classifier: Development Status :: 5 - Production/Stable
Classifier: Topic :: Software Development :: Libraries :: Python Modules
Classifier: License :: OSI Approved :: MIT License
Classifier: Programming Language :: Python :: 2.6
Classifier: Programming Language :: Python :: 2.7
Classifier: Programming Language :: Python :: 3
Classifier: Programming Language :: Python :: 3.2
Classifier: Programming Language :: Python :: 3.3
Classifier: Programming Language :: Python :: 3.4
Classifier: Programming Language :: Python :: 3.5
Requires-Dist: phoopy-console (<1.3.0,>=1.2.0)
Requires-Dist: phoopy-http (>=1.0.5)
Requires-Dist: phoopy-kernel (<1.3.0,>=1.2.0)
Requires-Dist: phoopy-yaml (<1.2.0,>=1.1.2)
